LICENSE
README.rst
setup.cfg
setup.py
bin/pspec
pytest_aspec/__init__.py
pytest_aspec/plugin.py
pytest_aspec/wrappers.py
pytest_aspec.egg-info/PKG-INFO
pytest_aspec.egg-info/SOURCES.txt
pytest_aspec.egg-info/dependency_links.txt
pytest_aspec.egg-info/entry_points.txt
pytest_aspec.egg-info/top_level.txt